ipi/__init__.py
ipi/engine/__init__.py
ipi/engine/atoms.py
ipi/engine/barostats.py
ipi/engine/beads.py
ipi/engine/cell.py
ipi/engine/ensembles.py
ipi/engine/forcefields.py
ipi/engine/forces.py
ipi/engine/initializer.py
ipi/engine/normalmodes.py
ipi/engine/outputs.py
ipi/engine/properties.py
ipi/engine/simulation.py
ipi/engine/system.py
ipi/engine/thermostats.py
ipi/engine/motion/__init__.py
ipi/engine/motion/al6xxx_kmc.py
ipi/engine/motion/alchemy.py
ipi/engine/motion/atomswap.py
ipi/engine/motion/constrained_dynamics.py
ipi/engine/motion/driven_dynamics.py
ipi/engine/motion/dynamics.py
ipi/engine/motion/geop.py
ipi/engine/motion/instanton.py
ipi/engine/motion/motion.py
ipi/engine/motion/multi.py
ipi/engine/motion/neb.py
ipi/engine/motion/phonons.py
ipi/engine/motion/planetary.py
ipi/engine/motion/ramp.py
ipi/engine/motion/replay.py
ipi/engine/motion/scphonons.py
ipi/engine/motion/stringmep.py
ipi/engine/motion/vscf.py
ipi/engine/smotion/__init__.py
ipi/engine/smotion/dmd.py
ipi/engine/smotion/metad.py
ipi/engine/smotion/multi.py
ipi/engine/smotion/remd.py
ipi/engine/smotion/smotion.py
ipi/external/__init__.py
ipi/external/importlib/__init__.py
ipi/external/importlib/bundledimportlib.py
ipi/inputs/__init__.py
ipi/inputs/atoms.py
ipi/inputs/barostats.py
ipi/inputs/beads.py
ipi/inputs/cell.py
ipi/inputs/ensembles.py
ipi/inputs/forcefields.py
ipi/inputs/forces.py
ipi/inputs/initializer.py
ipi/inputs/interface.py
ipi/inputs/normalmodes.py
ipi/inputs/outputs.py
ipi/inputs/prng.py
ipi/inputs/simulation.py
ipi/inputs/system.py
ipi/inputs/thermostats.py
ipi/inputs/motion/__init__.py
ipi/inputs/motion/al6xxx_kmc.py
ipi/inputs/motion/alchemy.py
ipi/inputs/motion/atomswap.py
ipi/inputs/motion/constrained_dynamics.py
ipi/inputs/motion/driven_dynamics.py
ipi/inputs/motion/dynamics.py
ipi/inputs/motion/geop.py
ipi/inputs/motion/instanton.py
ipi/inputs/motion/motion.py
ipi/inputs/motion/neb.py
ipi/inputs/motion/phonons.py
ipi/inputs/motion/planetary.py
ipi/inputs/motion/ramp.py
ipi-3.1.6.dist-info/METADATA
ipi-3.1.6.dist-info/WHEEL
ipi-3.1.6.dist-info/license_GPL.txt
ipi-3.1.6.dist-info/license_MIT.txt
ipi-3.1.6.dist-info/top_level.txt
ipi-3.1.6.dist-info/RECORD
