Metadata-Version: 2.1
Name: ipi
Version: 3.1.6
Summary: A Python interface for ab initio path integral molecular dynamics simulations
Home-page: http://ipi-code.org
Author: The i-PI developers
Author-email: ipi.managers@gmail.com
Project-URL: Documentation, https://ipi-code.org/i-pi
Project-URL: Repository, https://github.com/i-pi/i-pi
Classifier: Development Status :: 5 - Production/Stable
Classifier: Environment :: Console
Classifier: Intended Audience :: Science/Research
Classifier: Operating System :: MacOS :: MacOS X
Classifier: Operating System :: POSIX :: Linux
Classifier: License :: OSI Approved :: GNU General Public License v3 (GPLv3)
Classifier: Programming Language :: Python :: 3
Classifier: Programming Language :: Python :: 3.8
Classifier: Programming Language :: Python :: 3.9
Classifier: Programming Language :: Python :: 3.10
Classifier: Programming Language :: Python :: 3.11
Classifier: Topic :: Scientific/Engineering :: Chemistry
Classifier: Topic :: Scientific/Engineering :: Physics
Requires-Python: >=3.8
License-File: licenses/license_GPL.txt
License-File: licenses/license_MIT.txt
Requires-Dist: numpy
